CHANGELOG.md
LICENSE
MANIFEST.in
README.md
setup.py
pip2pkgbuild/__init__.py
pip2pkgbuild/__main__.py
pip2pkgbuild/pip2pkgbuild.py
pip2pkgbuild.egg-info/PKG-INFO
pip2pkgbuild.egg-info/SOURCES.txt
pip2pkgbuild.egg-info/dependency_links.txt
pip2pkgbuild.egg-info/entry_points.txt
pip2pkgbuild.egg-info/top_level.txt