Metadata-Version: 2.1
Name: pip2pkgbuild
Version: 0.5.0
Summary: Generate PKGBUILD file for a Python module from PyPI
Home-page: https://github.com/wenLiangcan/pip2pkgbuild
Author: wenLiangcan
Author-email: boxeed@gmail.com
License: MIT
Keywords: Packaging ArchLinux PKGBUILD
Platform: any
Classifier: Development Status :: 4 - Beta
Classifier: Environment :: Console
Classifier: Intended Audience :: End Users/Desktop
Classifier: License :: OSI Approved :: MIT License
Classifier: Natural Language :: English
Classifier: Operating System :: OS Independent
Classifier: Programming Language :: Python :: 2
Classifier: Programming Language :: Python :: 2.7
Classifier: Programming Language :: Python :: 3
Classifier: Programming Language :: Python :: 3.2
Classifier: Programming Language :: Python :: 3.3
Classifier: Programming Language :: Python :: 3.4
Classifier: Programming Language :: Python :: 3.5
Classifier: Programming Language :: Python :: 3.6
Classifier: Topic :: Software Development :: Build Tools
Classifier: Topic :: Software Development :: Code Generators
Classifier: Topic :: System :: Software Distribution
Classifier: Topic :: Utilities
License-File: LICENSE
